md2workflow/__init__.py
md2workflow/cli.py
md2workflow/markdown.py
md2workflow/schedule.py
md2workflow/workflow.py
md2workflow/backend/__init__.py
md2workflow/backend/genericbackend.py
md2workflow/backend/jirabackend.py
md2workflow/backend/redminebackend.py
md2workflow/backend/jirabackend/__init__.py
md2workflow/backend/redminebackend/__init__.py
md2workflow/validation/__init__.py
md2workflow/validation/config_validation.py
md2workflow/validation/jira_validation.py
md2workflow/validation/project_validation.py
md2workflow/validation/redmine_validation.py
md2workflow/validation/jira_validation/__init__.py
md2workflow/validation/redmine_validation/__init__.py
md2workflow-1.4.19.data/data/share/md2workflow/config/jira-example.conf
md2workflow-1.4.19.data/data/share/md2workflow/config/local.conf
md2workflow-1.4.19.data/data/share/md2workflow/config/redmine-example.conf
md2workflow-1.4.19.data/data/share/md2workflow/example/alpha.md
md2workflow-1.4.19.data/data/share/md2workflow/example/beta.md
md2workflow-1.4.19.data/data/share/md2workflow/example/example.ics
md2workflow-1.4.19.data/data/share/md2workflow/example/ga.md
md2workflow-1.4.19.data/data/share/md2workflow/example/jira-fields.json
md2workflow-1.4.19.data/data/share/md2workflow/example/my_project.conf
md2workflow-1.4.19.data/data/share/md2workflow/example/project_config.md
md2workflow-1.4.19.data/data/share/md2workflow/example/rc.md
md2workflow-1.4.19.data/data/share/md2workflow/example/repetitiveTasksForMilestones.md
md2workflow-1.4.19.dist-info/LICENSE
md2workflow-1.4.19.dist-info/METADATA
md2workflow-1.4.19.dist-info/WHEEL
md2workflow-1.4.19.dist-info/entry_points.txt
md2workflow-1.4.19.dist-info/top_level.txt
md2workflow-1.4.19.dist-info/RECORD
