Metadata-Version: 2.1
Name: md2workflow
Version: 1.4.19
Summary: Create a JIRA or other Workflow from markdown files.
Home-page: https://github.com/lkocman/md2workflow.git
Author: Lubos Kocman
Author-email: Lubos.Kocman@suse.com
License: GPLv3
Keywords: SUSE,Workflow,JIRA,Process,Markdown,Release Management
Platform: UNKNOWN
Classifier: Topic :: Text Processing :: Markup
Classifier: Topic :: Utilities
Classifier: License :: OSI Approved :: GNU General Public License v3 (GPLv3)
Requires-Dist: jira
Requires-Dist: python-redmine
